extended_approval/__init__.py
extended_approval/admin_urls.py
extended_approval/extension.py
extended_approval/forms.py
extended_approval/static/staticfiles.json
extended_approval/static/js/default.min.6f61c53bbff4.js
extended_approval/static/js/default.min.js
extended_approval/static/js/extension.ee9dab51f810.ts
extended_approval/static/js/extension.js
extended_approval/static/js/extension.js.map
extended_approval/static/js/extension.ts
rbExtendedApproval-1.2.7.dist-info/LICENSE
rbExtendedApproval-1.2.7.dist-info/METADATA
rbExtendedApproval-1.2.7.dist-info/WHEEL
rbExtendedApproval-1.2.7.dist-info/entry_points.txt
rbExtendedApproval-1.2.7.dist-info/top_level.txt
rbExtendedApproval-1.2.7.dist-info/RECORD
